LICENSE
MANIFEST.in
README.md
VERSION
requirements-test.txt
requirements.txt
setup.py
test_macro/__init__.py
test_macro/macro.py
test_macro.egg-info/PKG-INFO
test_macro.egg-info/SOURCES.txt
test_macro.egg-info/dependency_links.txt
test_macro.egg-info/entry_points.txt
test_macro.egg-info/not-zip-safe
test_macro.egg-info/requires.txt
test_macro.egg-info/top_level.txt
test_macro/cases/__init__.py
test_macro/cases/case.py
test_macro/cases/file.py
test_macro/cases/yaml.py
test_macro/exes/__init__.py
test_macro/fors/__init__.py
test_macro/fors/recorder.py
test_macro/parser/__init__.py