Metadata-Version: 2.1
Name: test-macro
Version: 0.1.5
Summary: a test automating library written in Python
Home-page: https://github.com/kerryeon/test-macro
Author: Ho Kim
Author-email: ho.kim@gnu.ac.kr
Maintainer: Ho Kim
Maintainer-email: ho.kim@gnu.ac.kr
License: MIT
Platform: UNKNOWN
